ctab_xtra_dp/README.md
ctab_xtra_dp/__init__.py
ctab_xtra_dp/requirements.txt
ctab_xtra_dp/datasets/Adult.csv
ctab_xtra_dp/datasets/__init__.py
ctab_xtra_dp/datasets/car.csv
ctab_xtra_dp/datasets/dataset_loader.py
ctab_xtra_dp/datasets/distribution_test_data.csv
ctab_xtra_dp/datasets/king.csv
ctab_xtra_dp/model/__init__.py
ctab_xtra_dp/model/ctabgan.py
ctab_xtra_dp/model/evaluation/__init__.py
ctab_xtra_dp/model/evaluation/evaluation.py
ctab_xtra_dp/model/evaluation/gower_mix.py
ctab_xtra_dp/model/pipeline/Categorical_preparation.py
ctab_xtra_dp/model/pipeline/Column_assigner.py
ctab_xtra_dp/model/pipeline/Log_preparation.py
ctab_xtra_dp/model/pipeline/__init__.py
ctab_xtra_dp/model/pipeline/data_preparation.py
ctab_xtra_dp/model/pipeline/data_type_assigner.py
ctab_xtra_dp/model/pipeline/null_value_transformer.py
ctab_xtra_dp/model/privacy_utils/DP_controller.py
ctab_xtra_dp/model/privacy_utils/__init__.py
ctab_xtra_dp/model/privacy_utils/rdp_accountant.py
ctab_xtra_dp/model/random/__init__.py
ctab_xtra_dp/model/random/random.py
ctab_xtra_dp/model/synthesizer/GMM_transformer.py
ctab_xtra_dp/model/synthesizer/__init__.py
ctab_xtra_dp/model/synthesizer/ctabgan_synthesizer.py
ctab_xtra_dp/model/synthesizer/transformer.py
ctab_xtra_dp-3.7.0.dist-info/METADATA
ctab_xtra_dp-3.7.0.dist-info/WHEEL
ctab_xtra_dp-3.7.0.dist-info/top_level.txt
ctab_xtra_dp-3.7.0.dist-info/RECORD
