Metadata-Version: 2.4
Name: ctab_xtra_dp
Version: 3.7.0
Summary: A sample Python package
Home-page: https://github.com/Kem0sabe/CTAB_XTRA_DP_REVISED/
Author: kem0sabe
Author-email: martivl@stud.ntnu.no
Classifier: Programming Language :: Python :: 3
Classifier: License :: OSI Approved :: MIT License
Classifier: Operating System :: OS Independent
Requires-Python: >=3.6
Requires-Dist: pandas
Requires-Dist: numpy
Requires-Dist: matplotlib
Requires-Dist: seaborn
Requires-Dist: scikit-learn
Requires-Dist: torch
Requires-Dist: tqdm
Requires-Dist: dython
Requires-Dist: pathlib
Requires-Dist: xgboost
Requires-Dist: catboost
Requires-Dist: lightgbm
Dynamic: author
Dynamic: author-email
Dynamic: classifier
Dynamic: description
Dynamic: description-content-type
Dynamic: home-page
Dynamic: requires-dist
Dynamic: requires-python
Dynamic: summary
